opx/__init__.py
opx/__main__.py
opx/cli.py
opx/debian.py
opx/workspace.py
opx/cmd/__init__.py
opx/cmd/assemble.py
opx/cmd/build.py
opx/cmd/init.py
opx/cmd/publish.py
opx/cmd/remove.py
opx/cmd/shell.py
opx/cmd/status.py
opx-1.0.1.dist-info/DESCRIPTION.rst
opx-1.0.1.dist-info/METADATA
opx-1.0.1.dist-info/RECORD
opx-1.0.1.dist-info/WHEEL
opx-1.0.1.dist-info/entry_points.txt
opx-1.0.1.dist-info/metadata.json
opx-1.0.1.dist-info/top_level.txt
tests/__init__.py
tests/test_debian.py
