Metadata-Version: 2.0
Name: opx
Version: 1.0.1
Summary: OpenSwitch Development Tool
Home-page: https://github.com/open-switch/tools_opx-py
Author: Tyler Heucke
Author-email: tyler.heucke@dell.com
License: MIT
Keywords: openswitch,opx
Platform: UNKNOWN
Classifier: Development Status :: 4 - Beta
Classifier: Intended Audience :: Developers
Classifier: License :: OSI Approved :: MIT License
Classifier: Natural Language :: English
Classifier: Operating System :: OS Independent
Classifier: Programming Language :: Python :: 3.6
Classifier: Programming Language :: Python :: Implementation :: CPython
Classifier: Programming Language :: Python :: Implementation :: PyPy
Requires-Dist: attrs
Requires-Dist: beautifultable
Requires-Dist: click
Requires-Dist: click-completion
Requires-Dist: click-log
Requires-Dist: colorama
Requires-Dist: deb-pkg-tools
Requires-Dist: docker
Requires-Dist: dockerpty
Requires-Dist: requests
Requires-Dist: sh
